{
  "schema_version": 1,
  "versions": [
    {
      "version": "0.2.0",
      "game_version": "<= 1.3.0",
      "date": "2026-06-01",
      "changelog": "Rendered landuse now resolves a wider OSM greenery palette (forest, wood, grass, meadow, cemetery, orchard, nature reserve, etc.) into the in-game park umbrella, so far more parkland, forest, and natural cover renders than in 0.1.x. Added hospital, port, convention / exhibition center, stadium and arena, and cultural-center demand. Multi-campus universities are now split across their campuses, attraction coverage expanded, and resident coverage restored for newly created villages.",
      "download": "https://github.com/ahkimn/subwaybuilder-tw-maps/releases/download/0.1.2/TNN.zip",
      "sha256": "2ae09e0c0489a1f307beac4f4094fab9a08a0a4896b64f3a6b3905161c5ac0ec"
    },
    {
      "version": "0.1.1",
      "game_version": "<=1.3.0",
      "date": "2026-05-25",
      "changelog": "Improved coastline accuracy and inland water/river representation, fixed neighbouring-city label bleed, and refined origin/destination commute distribution.",
      "download": "https://github.com/ahkimn/subwaybuilder-tw-maps/releases/download/0.1.1/TNN.zip",
      "sha256": "0135ef356fb2631dc561f2d66391ebdf65f2c3dbd660d199f58e2f54deb30724"
    },
    {
      "version": "0.1.0",
      "game_version": "<=1.3.0",
      "date": "2026-05-24",
      "changelog": "New in 0.1.0",
      "download": "https://github.com/ahkimn/subwaybuilder-tw-maps/releases/download/0.1.0/TNN.zip",
      "sha256": "7dc8e85c839d294abf5d228016a6dde8e214033378dc13fd9e3a045fd0b3c694"
    }
  ]
}
